{"cameraMode":{"drawMode":0,"name":"Shaded","section":"Shading Mode"},"sceneLighting":true,"audioPlay":false,"sceneViewState":{"showFog":true,"showMaterialUpdate":false,"showSkybox":true,"showFlares":true,"showImageEffects":true,"showParticleSystems":true},"in2DMode":false,"pivot":{"x":329.9794921875,"y":117.17970275878906,"z":98.58221435546875},"rotation":{"x":-0.2365230917930603,"y":-0.013993972912430764,"z":0.003406684612855315,"w":-0.9715239405632019},"size":459.2763671875,"orthographic":false}